TP3_archi/composants.vhd
---ALU du TP1 en version comportementale

library IEEE;
use IEEE.STD_LOGIC_1164.ALL;
use ieee.numeric_std.all;

entity ALU is
  port (
    R_e0: in STD_LOGIC_VECTOR(7 downto 0);
    R_e1: in STD_LOGIC_VECTOR(7 downto 0);
    Op: in STD_LOGIC_VECTOR(1 downto 0);
    R_s: out STD_LOGIC_VECTOR(7 downto 0)
    );
end entity;

architecture arch_ALU_comportemental of ALU is
begin
  process(Op, R_e0, R_e1)
  begin
    if R_e0 = "UUUUUUUU" or R_e1 = "UUUUUUUU" then
      R_s <= "UUUUUUUU";
    else
      if Op = "00" then
        R_s <= std_logic_vector(to_unsigned(to_integer(unsigned(R_e0)) + to_integer(unsigned(R_e1)), R_s'length));
      elsif Op = "01" then
        R_s <= std_logic_vector(to_signed(to_integer(unsigned(R_e0)) - to_integer(unsigned(R_e1)), R_s'length));
      elsif Op = "10" then
        R_s <= R_e0 and R_e1;
      else
        R_s <= R_e1;
      end if;
    end if;
  end process;
end architecture;


---Bascule D du TP2 en version comportementale
library IEEE;
use IEEE.STD_LOGIC_1164.ALL;

entity bascule_D is
  port (
    e: in STD_LOGIC;
    clk: in STD_LOGIC;
    rst: in STD_LOGIC;
    set: in STD_LOGIC;
    s: out STD_LOGIC
    );
end entity;

architecture arch_bascule_D of bascule_D is
begin
  process(clk, rst, set)
  begin
    if rst = '0' then
      s <= '0';
    elsif set = '0' then
      s <= '1';
    elsif rising_edge(clk) then
      s <= e;
    end if;
  end process;
end architecture;

---Registre 8 bits du TP2 en version comportementale

library IEEE;
use IEEE.STD_LOGIC_1164.ALL;

entity r8bits is
  port(
    R_in: in STD_LOGIC_VECTOR(7 downto 0);
    WR: in STD_LOGIC;
    rst: in STD_LOGIC;
    clk: in STD_LOGIC;
    R_out: out STD_LOGIC_VECTOR(7 downto 0)
    );
end entity;

architecture arch_r8bits_comp of r8bits is
begin
  process(clk, rst)
  begin
    if rst = '0' then
      R_out <= "00000000";
    elsif rising_edge(clk) then
      if WR = '1' then
        R_out <= R_in;
      end if;
    end if;
  end process;
end architecture;

---Banc de registres du TP2 en version comportementale
library IEEE;
use IEEE.STD_LOGIC_1164.ALL;
use ieee.numeric_std.all;

entity banc is
  port(
    reg_0_id: in STD_LOGIC_VECTOR(2 downto 0);
    reg_1_id: in STD_LOGIC_VECTOR(2 downto 0);
    reg_write_val: in STD_LOGIC_VECTOR(7 downto 0);
    WR: in STD_LOGIC;
    clk: in STD_LOGIC;
    rst: in STD_LOGIC;
    reg_0_val: out STD_LOGIC_VECTOR(7 downto 0);
    reg_1_val: out STD_LOGIC_VECTOR(7 downto 0)
    );
end entity;

architecture arch_banc_comportemental of banc is
  type reg_array is array (0 to 7) of STD_LOGIC_VECTOR(7 downto 0);
  signal regs: reg_array;
begin
  -- 1 process for WR
  process(clk, rst)
  begin
    if rst = '0' then
      for i in 0 to 7 loop
        regs(i) <= "00000000";
      end loop;
    
    elsif rising_edge(clk) then 
      if WR = '1' then
        regs(to_integer(unsigned(reg_0_id))) <= reg_write_val;
      end if;
    end if;
  end process;

  -- 1 process for Reads
  process(reg_0_id, reg_1_id, regs)
  begin
    if reg_0_id = "UUU" or reg_1_id = "UUU" then
      reg_0_val <= "UUUUUUUU";
      reg_1_val <= "UUUUUUUU";
    else
      reg_0_val <= regs(to_integer(unsigned(reg_0_id)));
      reg_1_val <= regs(to_integer(unsigned(reg_1_id)));
    end if;
  end process;
end architecture;

TP3_archi/TP3.vhd
-- Architecture 2. Sujet de TP 3 (seances 5 et 6).
-- Implementation d'un processeur simplifié
-- Author: T. Carle (thomas.carle@irit.fr)


-- I. Assemblage de l'ALU et du banc de registres
-- I.0. MUX 2 -> 1 8 bits
library IEEE;
use IEEE.STD_LOGIC_1164.ALL;

entity MUX2_1_8 is
  port (
    e0: in STD_LOGIC_VECTOR(7 downto 0);
    e1: in STD_LOGIC_VECTOR(7 downto 0);
    c: in STD_LOGIC;
    o: out STD_LOGIC_VECTOR(7 downto 0)
    );
end entity;

architecture arch_MUX2_1_8 of MUX2_1_8 is
begin
  o <= e1 when c = '1'
       else e0;
end architecture;
-------------------------------------------------------------------

-- I.1. processeur
library IEEE;
use IEEE.STD_LOGIC_1164.ALL;

entity proc_v0 is
  port (
    op: in STD_LOGIC_VECTOR(1 downto 0);
    reg_0_id: in STD_LOGIC_VECTOR(2 downto 0);
    reg_1_id: in STD_LOGIC_VECTOR(2 downto 0);
    rst: in STD_LOGIC;
    clk: in STD_LOGIC;
    WR_bank: in STD_LOGIC
    );
end entity;

architecture proc_v0_struct of proc_v0 is
  signal mux_out, alu_out, bank_out_0, bank_out_1, mux_in_5_3 : STD_LOGIC_VECTOR(7 downto 0);
  signal Op_out_and : STD_LOGIC;
  
  begin
   mux_in_5_3 <= "00000" & reg_1_id;
   Op_out_and <= Op(0) and Op(1);
      mu: entity work.MUX2_1_8
	port map(e0 => bank_out_1,
		 e1 => mux_in_5_3,
		 c => Op_out_and,
		 o => mux_out);
		 
      al : entity work.ALU
        port map(R_e0 => bank_out_0,
                 R_e1 => mux_out,
                 R_s => alu_out,
                 Op => op);

      ba : entity work.banc
        port map(reg_0_id => reg_0_id,
                 reg_1_id => reg_1_id,
                 reg_write_val => alu_out,
                 WR => WR_bank,
                 clk => clk,
                 rst => rst,
                 reg_0_val => bank_out_0,
                 reg_1_val => bank_out_1);
end architecture;

-------------------------------------------------------------------

--II. Ajout d'un sequenceur pour obtenir le processeur simplifie
--II.1. Sequenceur
library IEEE;
use IEEE.STD_LOGIC_1164.ALL;

entity sequencer is
  port (
    init : in STD_LOGIC;
    clk: in STD_LOGIC;
    WR_instr: out STD_LOGIC;
    WR_bank: out STD_LOGIC
    );
end entity;

architecture sequencer_struct of sequencer is
  signal b_out_1, b_out_2:STD_LOGIC;
  begin
    
    baun : entity work.bascule_D
      port map(e => b_out_2,
               clk => clk,
	       rst => init,
	       set => init,
               s=> b_out_1);
    
    badeux : entity work.bascule_D
      port map(e=>b_out_1,
               clk=>clk,
               rst => init,
               set => init,
               s => b_out_2);
end architecture;
               

-------------------------------------------------------------------
--II.2. Assemblage du processeur
library IEEE;
use IEEE.STD_LOGIC_1164.ALL;

entity proc_v1 is
  port (
    instr: in STD_LOGIC_VECTOR(7 downto 0);
    Init: in STD_LOGIC;
    rst: in STD_LOGIC;
    clk: in STD_LOGIC
    );
end entity;

architecture arch_proc_v1 of proc_v1 is 
signal WR_bank_out: STD_LOGIC;
signal WR_instr_out: STD_LOGIC;
signal R_out_reg: STD_LOGIC_VECTOR(7 downto 0);
  begin
  
  se: entity work.sequencer
     port map(init => Init,
              clk => clk,
              WR_instr => WR_instr_out,
              WR_bank => WR_bank_out);

  re: entity work.r8bits
     port map( R_in => instr,
               WR => WR_instr_out,
               rst => '1',
               clk => clk,
               R_out => R_out_reg);

  pr: entity work.proc_v0
     port map(op => R_out_reg(7 downto 6),
              reg_0_id => R_out_reg(5 downto 3),
              reg_1_id => R_out_reg(2 downto 0),
              rst => rst,
              clk => clk,
              WR_bank => WR_bank_out);
end architecture;
               
-------------------------------------------------------------------

TP3_archi/sabour.fayçal/TP3_test.vhd
-- Architecture 2. Sujet de TP 3 (seances 5 et 6).
-- Implementation d'un processeur simplifié -- banc de test
-- Author: T. Carle (thomas.carle@irit.fr)

-- I. Processeur v0
library IEEE;
use IEEE.STD_LOGIC_1164.ALL;

entity proc_v0_test is
end entity;

architecture arch_proc_v0_test of proc_v0_test is

  signal op_in : STD_LOGIC_VECTOR(1 downto 0);
  signal reg_0_id, reg_1_id: STD_LOGIC_VECTOR(2 downto 0);
  signal rst, clk, WR_bank: STD_LOGIC;

begin
  proc: entity work.proc_v0
    port map(op_in, reg_0_id, reg_1_id, rst, clk, WR_bank);

  process
  begin
    -- Initialize all registers to 0
    rst <= '0';
    clk <= '0';
    reg_0_id <= "000";
    reg_1_id <= "000";
    WR_bank <= '0';
    wait for 5 ns;
    rst <= '1';
    wait for 5 ns;

    --MOV R0, #4
    op_in <= "11";
    reg_0_id <= "000";
    reg_1_id <= "100";
    wait for 5 ns;
    clk <= '1';
    wait for 5 ns;
    clk <= '0';
    WR_bank <= '1';
    wait for 5 ns;
    clk <= '1';
    wait for 5 ns;
    clk <= '0';
    WR_bank <= '0';

    -- MOV R2, #3
    reg_0_id <= "010";
    reg_1_id <= "011";
    wait for 5 ns;
    clk <= '1';
    wait for 5 ns;
    clk <= '0';
    WR_bank <= '1';
    wait for 5 ns;
    clk <= '1';
    wait for 5 ns;
    clk <= '0';
    WR_bank <= '0';

    -- ADD R0, R0, R2
    op_in <= "00";
    reg_0_id <= "000";
    reg_1_id <= "010";
    wait for 5 ns;
    clk <= '1';
    wait for 5 ns;
    clk <= '0';
    WR_bank <= '1';
    wait for 5 ns;
    clk <= '1';
    wait for 5 ns;
    clk <= '0';
    WR_bank <= '0';

    -- MOV R7, #7
    op_in <= "11";
    reg_0_id <= "111";
    reg_1_id <= "111";
    wait for 5 ns;
    clk <= '1';
    wait for 5 ns;
    clk <= '0';
    WR_bank <= '1';
    wait for 5 ns;
    clk <= '1';
    wait for 5 ns;
    clk <= '0';
    WR_bank <= '0';
    
    --SUB R0, R0, R7
    op_in <= "01";
    reg_0_id <= "000";
    reg_1_id <= "111";
    wait for 5 ns;
    clk <= '1';
    wait for 5 ns;
    clk <= '0';
    WR_bank <= '1';
    wait for 5 ns;
    clk <= '1';
    wait for 5 ns;
    clk <= '0';
    WR_bank <= '0';
    wait for 5 ns;
    wait;
  end process;
end architecture;
--------------------------------------------------------------------------------------

--II. Processeur v1
-- Exemple de programmation
library IEEE;
use IEEE.STD_LOGIC_1164.ALL;

entity proc_v1_test is
end entity;

architecture arch_proc_v1_test of proc_v1_test is
  signal instr : STD_LOGIC_VECTOR(7 downto 0);
  signal rst, clk, Init: STD_LOGIC;

begin
  proc: entity work.proc_v1
    port map(instr, Init, rst, clk);

  process
  begin
    -- Initialize all registers to 0
    rst <= '0';
    clk <= '0';
    Init <= '0';
    wait for 5 ns;
    rst <= '1';
    Init <= '1';

    --MOV R0, #4
    instr <= "11000100";
    wait for 5 ns;
    clk <= '1';
    wait for 5 ns;
    clk <= '0';
    wait for 5 ns;
    clk <= '1';
    wait for 5 ns;
    clk <= '0';

    --MOV R2, #3
    instr <= "11010011";
    wait for 5 ns;
    clk <= '1';
    wait for 5 ns;
    clk <= '0';
    wait for 5 ns;
    clk <= '1';
    wait for 5 ns;
    clk <= '0';

    --ADD R0, R0, R2
    instr <= "00000010";
    wait for 5 ns;
    clk <= '1';
    wait for 5 ns;
    clk <= '0';
    wait for 5 ns;
    clk <= '1';
    wait for 5 ns;
    clk <= '0';

    --MOV R7, #7
    instr <= "11111111";
    wait for 5 ns;
    clk <= '1';
    wait for 5 ns;
    clk <= '0';
    wait for 5 ns;
    clk <= '1';
    wait for 5 ns;
    clk <= '0';

    --SUB R0, R0, R7
    instr <= "01000111";
    wait for 5 ns;
    clk <= '1';
    wait for 5 ns;
    clk <= '0';
    wait for 5 ns;
    clk <= '1';
    wait for 5 ns;
    clk <= '0';


    --AND R7, R7, R2
    instr <= "10111010";
    wait for 5 ns;
    clk <= '1';
    wait for 5 ns;
    clk <= '0';
    wait for 5 ns;
    clk <= '1';
    wait for 5 ns;
    clk <= '0';

    wait;
  end process;
end architecture;


--3+2
library IEEE;
use IEEE.STD_LOGIC_1164.ALL;

entity calcul_1 is
end entity;

architecture arch_calcul_1 of calcul_1 is
signal rst, clk, Init: STD_LOGIC;
signal op_in: STD_LOGIC_VECTOR(1 downto 0);
signal reg0_in, reg1_in: STD_LOGIC_VECTOR(2 downto 0);
signal instr: STD_LOGIC_VECTOR(7 downto 0);

begin
  instr <= op_in & reg0_in & reg1_in;
  proc: entity work.proc_v1
    port map(instr, Init, rst, clk);

  process
  begin
  
   rst <= '0';
   clk <= '0';
   Init <= '0';
   wait for 5 ns;
   rst <= '1';
   Init <= '1';


  op_in <= "11";
  reg0_in <= "000";
  reg1_in <= "011";
  wait for 5 ns;

  clk <= '1';
  wait for 5 ns;
  clk <= '0';
  wait for 5 ns;
  clk <= '1';
  wait for 5 ns;
  clk <= '0'; 
  wait for 5 ns;

  reg0_in <= "001";
  reg1_in <= "010";
  wait for 5 ns;

  clk <= '1';
  wait for 5 ns;
  clk <= '0';
  wait for 5 ns;
  clk <= '1';
  wait for 5 ns;
  clk <= '0';
  wait for 5 ns;

  op_in <= "00";
  reg0_in <= "000";
  reg1_in <= "001";
  wait for 5 ns;

  clk <= '1';
  wait for 5 ns;
  clk <= '0';
  wait for 5 ns;
  clk <= '1';
  wait for 5 ns;
  clk <= '0';
  wait for 5 ns;
  clk <= '1';
  wait for 5 ns;
  clk <= '0';
  wait for 5 ns;

  wait;
  end process;
end architecture;
   

--5+(3-2)
library IEEE;
use IEEE.STD_LOGIC_1164.ALL;

entity calcul_2 is
end entity;

architecture arch_calcul_2 of calcul_2 is
signal rst, clk, Init: STD_LOGIC;
signal op_in: STD_LOGIC_VECTOR(1 downto 0);
signal reg0_in, reg1_in: STD_LOGIC_VECTOR(2 downto 0);
signal instr: STD_LOGIC_VECTOR(7 downto 0);

begin
  instr <= op_in & reg0_in & reg1_in;
  proc: entity work.proc_v1
    port map(instr, Init, rst, clk);

  process
  begin
  
   rst <= '0';
   clk <= '0';
   Init <= '0';
   wait for 5 ns;
   rst <= '1';
   Init <= '1';

   op_in <= "11";
		reg0_in <= "000";
		reg1_in <= "011";
		wait for 5 ns;

		clk <= '1';
		wait for 5 ns;
		clk <= '0';
		wait for 5 ns;
		clk <= '1';
		wait for 5 ns;
		clk <= '0';
		wait for 5 ns;

		reg0_in <= "001";
		reg1_in <= "010";
		wait for 5 ns;

		clk <= '1';
		wait for 5 ns;
		clk <= '0';
		wait for 5 ns;
		clk <= '1';
		wait for 5 ns;
		clk <= '0';
		wait for 5 ns;

		op_in <= "01";
		reg0_in <= "000";
		reg1_in <= "001";
		wait for 5 ns;

		clk <= '1';
		wait for 5 ns;
		clk <= '0';
		wait for 5 ns;
		clk <= '1';
		wait for 5 ns;
		clk <= '0';
		wait for 5 ns;

		op_in <= "11";
		reg0_in <= "001";
		reg1_in <= "101";
		wait for 5 ns;

		clk <= '1';
		wait for 5 ns;
		clk <= '0';
		wait for 5 ns;
		clk <= '1';
		wait for 5 ns;
		clk <= '0';
		wait for 5 ns;

		op_in <= "00";
		reg0_in <= "000";
		reg1_in <= "001";
		wait for 5 ns;

		clk <= '1';
		wait for 5 ns;
		clk <= '0';
		wait for 5 ns;
		clk <= '1';
		wait for 5 ns;
		clk <= '0';
		wait for 5 ns;
		clk <= '1';
		wait for 5 ns;
		clk <= '0';
		wait for 5 ns;

		wait;
	end process;
end architecture;


--6 and 2
library IEEE;
use IEEE.STD_LOGIC_1164.ALL;

entity calcul_3 is
end entity;

architecture arch_calcul_3 of calcul_3 is
signal rst, clk, Init: STD_LOGIC;
signal op_in: STD_LOGIC_VECTOR(1 downto 0);
signal reg0_in, reg1_in: STD_LOGIC_VECTOR(2 downto 0);
signal instr: STD_LOGIC_VECTOR(7 downto 0);

begin
  instr <= op_in & reg0_in & reg1_in;
  proc: entity work.proc_v1
    port map(instr, Init, rst, clk);

  process
  begin
  
   rst <= '0';
   clk <= '0';
   Init <= '0';
   wait for 5 ns;
   rst <= '1';
   Init <= '1';

  op_in <= "11";
		reg0_in <= "000";
		reg1_in <= "011";
		wait for 5 ns;

		clk <= '1';
		wait for 5 ns;
		clk <= '0';
		wait for 5 ns;
		clk <= '1';
		wait for 5 ns;
		clk <= '0';
		wait for 5 ns;


		reg0_in <= "001";
		reg1_in <= "010";
		wait for 5 ns;

		clk <= '1';
		wait for 5 ns;
		clk <= '0';
		wait for 5 ns;
		clk <= '1';
		wait for 5 ns;
		clk <= '0';
		wait for 5 ns;


		op_in <= "10";
		reg0_in <= "000";
		reg1_in <= "001";
		wait for 5 ns;

		clk <= '1';
		wait for 5 ns;
		clk <= '0';
		wait for 5 ns;
		clk <= '1';
		wait for 5 ns;
		clk <= '0';
		wait for 5 ns;
		clk <= '1';
		wait for 5 ns;
		clk <= '0';
		wait for 5 ns;

		wait;
	end process;
end architecture;

--10 + 5 - 2 + 12
library IEEE;
use IEEE.STD_LOGIC_1164.ALL;

entity calcul_4 is
end entity;

architecture arch_calcul_4 of calcul_4 is
signal rst, clk, Init: STD_LOGIC;
signal op_in: STD_LOGIC_VECTOR(1 downto 0);
signal reg0_in, reg1_in: STD_LOGIC_VECTOR(2 downto 0);
signal instr: STD_LOGIC_VECTOR(7 downto 0);

begin
  instr <= op_in & reg0_in & reg1_in;
  proc: entity work.proc_v1
    port map(instr, Init, rst, clk);

  process
  begin
  
   rst <= '0';
   clk <= '0';
   Init <= '0';
   wait for 5 ns;
   rst <= '1';
   Init <= '1';

   init <= '0';
		init <= '1';
		rst <= '1';

	
		op_in <= "11";
		reg0_in <= "000";
		reg1_in <= "101";
		wait for 5 ns;

		clk <= '1';
		wait for 5 ns;
		clk <= '0';
		wait for 5 ns;
		clk <= '1';
		wait for 5 ns;
		clk <= '0';
		wait for 5 ns;

	
		reg0_in <= "001";
		wait for 5 ns;

		clk <= '1';
		wait for 5 ns;
		clk <= '0';
		wait for 5 ns;
		clk <= '1';
		wait for 5 ns;
		clk <= '0';
		wait for 5 ns;


		op_in <= "00";
		reg0_in <= "000";
		reg1_in <= "001";
		wait for 5 ns;

		clk <= '1';
		wait for 5 ns;
		clk <= '0';
		wait for 5 ns;
		clk <= '1';
		wait for 5 ns;
		clk <= '0';
		wait for 5 ns;



		clk <= '1';
		wait for 5 ns;
		clk <= '0';
		wait for 5 ns;
		clk <= '1';
		wait for 5 ns;
		clk <= '0';
		wait for 5 ns;

	
		op_in <= "11";
		reg0_in <= "001";
		reg1_in <= "010";
		wait for 5 ns;

		clk <= '1';
		wait for 5 ns;
		clk <= '0';
		wait for 5 ns;
		clk <= '1';
		wait for 5 ns;
		clk <= '0';
		wait for 5 ns;


		op_in <= "01";
		reg0_in <= "000";
		reg1_in <= "001";
		wait for 5 ns;

		clk <= '1';
		wait for 5 ns;
		clk <= '0';
		wait for 5 ns;
		clk <= '1';
		wait for 5 ns;
		clk <= '0';
		wait for 5 ns;


		op_in <= "11";
		reg0_in <= "001";
		reg1_in <= "110";
		wait for 5 ns;

		clk <= '1';
		wait for 5 ns;
		clk <= '0';
		wait for 5 ns;
		clk <= '1';
		wait for 5 ns;
		clk <= '0';
		wait for 5 ns;


		reg0_in <= "010";
		wait for 5 ns;

		clk <= '1';
		wait for 5 ns;
		clk <= '0';
		wait for 5 ns;
		clk <= '1';
		wait for 5 ns;
		clk <= '0';
		wait for 5 ns;


		op_in <= "00";
		reg0_in <= "001";
		reg1_in <= "010";
		wait for 5 ns;

		clk <= '1';
		wait for 5 ns;
		clk <= '0';
		wait for 5 ns;
		clk <= '1';
		wait for 5 ns;
		clk <= '0';
		wait for 5 ns;


		op_in <= "00";
		reg0_in <= "000";
		reg1_in <= "001";
		wait for 5 ns;

		clk <= '1';
		wait for 5 ns;
		clk <= '0';
		wait for 5 ns;
		clk <= '1';
		wait for 5 ns;
		clk <= '0';
		wait for 5 ns;
		clk <= '1';
		wait for 5 ns;
		clk <= '0';
		wait for 5 ns;

		wait;
	end process;
end architecture;

TP3_archi/calcul_4.vcd
$date
  Sat Dec  4 00:10:38 2021
$end
$version
  GHDL v0
$end
$timescale
  1 fs
$end
$scope module standard $end
$upscope $end
$scope module std_logic_1164 $end
$upscope $end
$scope module numeric_std $end
$upscope $end
$scope module calcul_4 $end
$var reg 1 ! rst $end
$var reg 1 " clk $end
$var reg 1 # init $end
$var reg 2 $ op_in[1:0] $end
$var reg 3 % reg0_in[2:0] $end
$var reg 3 & reg1_in[2:0] $end
$var reg 8 ' instr[7:0] $end
$scope module proc $end
$var reg 8 ( instr[7:0] $end
$var reg 1 ) init $end
$var reg 1 * rst $end
$var reg 1 + clk $end
$var reg 1 , wr_bank_out $end
$var reg 1 - wr_instr_out $end
$var reg 8 . r_out_reg[7:0] $end
$scope module se $end
$var reg 1 / init $end
$var reg 1 0 clk $end
$var reg 1 1 wr_instr $end
$var reg 1 2 wr_bank $end
$var reg 1 3 b_out_1 $end
$var reg 1 4 b_out_2 $end
$scope module baun $end
$var reg 1 5 e $end
$var reg 1 6 clk $end
$var reg 1 7 rst $end
$var reg 1 8 set $end
$var reg 1 9 s $end
$upscope $end
$scope module badeux $end
$var reg 1 : e $end
$var reg 1 ; clk $end
$var reg 1 < rst $end
$var reg 1 = set $end
$var reg 1 > s $end
$upscope $end
$upscope $end
$scope module re $end
$var reg 8 ? r_in[7:0] $end
$var reg 1 @ wr $end
$var reg 1 A rst $end
$var reg 1 B clk $end
$var reg 8 C r_out[7:0] $end
$upscope $end
$scope module pr $end
$var reg 2 D op[1:0] $end
$var reg 3 E reg_0_id[2:0] $end
$var reg 3 F reg_1_id[2:0] $end
$var reg 1 G rst $end
$var reg 1 H clk $end
$var reg 1 I wr_bank $end
$var reg 8 J mux_out[7:0] $end
$var reg 8 K alu_out[7:0] $end
$var reg 8 L bank_out_0[7:0] $end
$var reg 8 M bank_out_1[7:0] $end
$var reg 8 N mux_in_5_3[7:0] $end
$var reg 1 O op_out_and $end
$scope module mu $end
$var reg 8 P e0[7:0] $end
$var reg 8 Q e1[7:0] $end
$var reg 1 R c $end
$var reg 8 S o[7:0] $end
$upscope $end
$scope module al $end
$var reg 8 T r_e0[7:0] $end
$var reg 8 U r_e1[7:0] $end
$var reg 2 V op[1:0] $end
$var reg 8 W r_s[7:0] $end
$upscope $end
$scope module ba $end
$var reg 3 X reg_0_id[2:0] $end
$var reg 3 Y reg_1_id[2:0] $end
$var reg 8 Z reg_write_val[7:0] $end
$var reg 1 [ wr $end
$var reg 1 \ clk $end
$var reg 1 ] rst $end
$var reg 8 ^ reg_0_val[7:0] $end
$var reg 8 _ reg_1_val[7:0] $end
$comment regs is not handled $end
$upscope $end
$upscope $end
$upscope $end
$upscope $end
$enddefinitions $end
#0
0!
0"
0#
bUU $
bUUU %
bUUU &
bUUUUUUUU '
bUUUUUUUU (
0)
0*
0+
U,
U-
bUUUUUUUU .
0/
00
U1
U2
03
04
05
06
07
08
09
0:
0;
0<
0=
0>
bUUUUUUUU ?
U@
1A
0B
bUUUUUUUU C
bUU D
bUUU E
bUUU F
0G
0H
UI
bUUUUUUUU J
bUUUUUUUU K
bUUUUUUUU L
bUUUUUUUU M
b00000UUU N
UO
bUUUUUUUU P
b00000UUU Q
UR
bUUUUUUUU S
bUUUUUUUU T
bUUUUUUUU U
bUU V
bUUUUUUUU W
bUUU X
bUUU Y
bUUUUUUUU Z
U[
0\
0]
bUUUUUUUU ^
bUUUUUUUU _
#5000000
1!
1#
b11 $
b000 %
b101 &
b11000101 '
b11000101 (
1)
1*
1/
17
18
1<
1=
b11000101 ?
1G
1]
#10000000
1"
1+
10
16
1;
1B
1H
1\
#15000000
0"
0+
00
06
0;
0B
0H
0\
#20000000
1"
1+
10
16
1;
1B
1H
1\
#25000000
0"
0+
00
06
0;
0B
0H
0\
#30000000
b001 %
b11001101 '
b11001101 (
b11001101 ?
#35000000
1"
1+
10
16
1;
1B
1H
1\
#40000000
0"
0+
00
06
0;
0B
0H
0\
#45000000
1"
1+
10
16
1;
1B
1H
1\
#50000000
0"
0+
00
06
0;
0B
0H
0\
#55000000
b00 $
b000 %
b001 &
b00000001 '
b00000001 (
b00000001 ?
#60000000
1"
1+
10
16
1;
1B
1H
1\
#65000000
0"
0+
00
06
0;
0B
0H
0\
#70000000
1"
1+
10
16
1;
1B
1H
1\
#75000000
0"
0+
00
06
0;
0B
0H
0\
#80000000
1"
1+
10
16
1;
1B
1H
1\
#85000000
0"
0+
00
06
0;
0B
0H
0\
#90000000
1"
1+
10
16
1;
1B
1H
1\
#95000000
0"
0+
00
06
0;
0B
0H
0\
#100000000
b11 $
b001 %
b010 &
b11001010 '
b11001010 (
b11001010 ?
#105000000
1"
1+
10
16
1;
1B
1H
1\
#110000000
0"
0+
00
06
0;
0B
0H
0\
#115000000
1"
1+
10
16
1;
1B
1H
1\
#120000000
0"
0+
00
06
0;
0B
0H
0\
#125000000
b01 $
b000 %
b001 &
b01000001 '
b01000001 (
b01000001 ?
#130000000
1"
1+
10
16
1;
1B
1H
1\
#135000000
0"
0+
00
06
0;
0B
0H
0\
#140000000
1"
1+
10
16
1;
1B
1H
1\
#145000000
0"
0+
00
06
0;
0B
0H
0\
#150000000
b11 $
b001 %
b110 &
b11001110 '
b11001110 (
b11001110 ?
#155000000
1"
1+
10
16
1;
1B
1H
1\
#160000000
0"
0+
00
06
0;
0B
0H
0\
#165000000
1"
1+
10
16
1;
1B
1H
1\
#170000000
0"
0+
00
06
0;
0B
0H
0\
#175000000
b010 %
b11010110 '
b11010110 (
b11010110 ?
#180000000
1"
1+
10
16
1;
1B
1H
1\
#185000000
0"
0+
00
06
0;
0B
0H
0\
#190000000
1"
1+
10
16
1;
1B
1H
1\
#195000000
0"
0+
00
06
0;
0B
0H
0\
#200000000
b00 $
b001 %
b010 &
b00001010 '
b00001010 (
b00001010 ?
#205000000
1"
1+
10
16
1;
1B
1H
1\
#210000000
0"
0+
00
06
0;
0B
0H
0\
#215000000
1"
1+
10
16
1;
1B
1H
1\
#220000000
0"
0+
00
06
0;
0B
0H
0\
#225000000
b000 %
b001 &
b00000001 '
b00000001 (
b00000001 ?
